<?xml version="1.0"?>
<menu>
  <item>
    <path>civicrm/dedupeidentifier</path>
    <page_callback>CRM_Identifyuser_Form_DedupeIdentifier</page_callback>
    <title>DedupeIdentifier</title>
    <access_callback>1</access_callback>
    <is_public>true</is_public>
  </item>
  <item>
    <path>civicrm/verifyotp</path>
    <page_callback>CRM_Identifyuser_Form_VerifyOTP</page_callback>
    <title>VerifyOTP</title>
    <access_callback>1</access_callback>
    <is_public>true</is_public>
  </item>
  <item>
    <path>civicrm/identifyusersetting</path>
    <page_callback>CRM_Identifyuser_Form_IdentifyUserSetting</page_callback>
    <title>IdentifyUserSetting</title>
    <access_arguments>access CiviCRM</access_arguments>
  </item>
</menu>
